CHANGELOG.txt
LICENSE.txt
MANIFEST.in
README.md
setup.py
okta_python.egg-info/SOURCES.txt
okta_python.egg-info/dependency_links.txt
okta_python.egg-info/requires.txt
okta_python.egg-info/top_level.txt
oktapython/__init__.py
oktapython/okta.py
oktapython/users.py
oktapython.egg-info/PKG-INFO
oktapython.egg-info/SOURCES.txt
oktapython.egg-info/dependency_links.txt
oktapython.egg-info/requires.txt
oktapython.egg-info/top_level.txt